manifestoo_core/__init__.py
manifestoo_core/addon.py
manifestoo_core/addons_set.py
manifestoo_core/exceptions.py
manifestoo_core/git_postversion.py
manifestoo_core/manifest.py
manifestoo_core/metadata.py
manifestoo_core/odoo_series.py
manifestoo_core/py.typed
manifestoo_core/core_addons/__init__.py
manifestoo_core/core_addons/addons-10.0-c.txt
manifestoo_core/core_addons/addons-10.0-e.txt
manifestoo_core/core_addons/addons-11.0-c.txt
manifestoo_core/core_addons/addons-11.0-e.txt
manifestoo_core/core_addons/addons-12.0-c.txt
manifestoo_core/core_addons/addons-12.0-e.txt
manifestoo_core/core_addons/addons-13.0-c.txt
manifestoo_core/core_addons/addons-13.0-e.txt
manifestoo_core/core_addons/addons-14.0-c.txt
manifestoo_core/core_addons/addons-14.0-e.txt
manifestoo_core/core_addons/addons-15.0-c.txt
manifestoo_core/core_addons/addons-15.0-e.txt
manifestoo_core/core_addons/addons-16.0-c.txt
manifestoo_core/core_addons/addons-16.0-e.txt
manifestoo_core/core_addons/addons-17.0-c.txt
manifestoo_core/core_addons/addons-17.0-e.txt
manifestoo_core/core_addons/addons-18.0-c.txt
manifestoo_core/core_addons/addons-18.0-e.txt
manifestoo_core/core_addons/addons-19.0-c.txt
manifestoo_core/core_addons/addons-19.0-e.txt
manifestoo_core/core_addons/addons-8.0-c.txt
manifestoo_core/core_addons/addons-8.0-e.txt
manifestoo_core/core_addons/addons-9.0-c.txt
manifestoo_core/core_addons/addons-9.0-e.txt
manifestoo_core-1.14.dist-info/METADATA
manifestoo_core-1.14.dist-info/WHEEL
manifestoo_core-1.14.dist-info/licenses/LICENSE
manifestoo_core-1.14.dist-info/RECORD
