Metadata-Version: 2.4
Name: manifestoo_core
Version: 1.14
Summary: A library to reason about Odoo addons manifests
Project-URL: Homepage, https://github.com/acsone/manifestoo-core
Project-URL: Documentation, https://manifestoo-core.readthedocs.io/en/stable/
Project-URL: Changelog, https://manifestoo-core.readthedocs.io/en/stable/changelog.html
Project-URL: Source, https://github.com/acsone/manifestoo-core
Author-email: Stéphane Bidoul <stephane.bidoul@acsone.eu>
License-File: LICENSE
Classifier: Development Status :: 4 - Beta
Classifier: Framework :: Odoo
Classifier: Intended Audience :: Developers
Classifier: License :: OSI Approved :: MIT License
Classifier: Operating System :: OS Independent
Classifier: Programming Language :: Python
Classifier: Programming Language :: Python :: 3
Classifier: Programming Language :: Python :: 3 :: Only
Requires-Python: >=3.7
Requires-Dist: importlib-resources; python_version < '3.9'
Requires-Dist: packaging
Requires-Dist: typing-extensions; python_version < '3.8'
Provides-Extra: doc
Requires-Dist: furo; extra == 'doc'
Requires-Dist: myst-parser; extra == 'doc'
Requires-Dist: sphinx; extra == 'doc'
Requires-Dist: sphinxcontrib-towncrier; extra == 'doc'
Requires-Dist: towncrier<22.8; extra == 'doc'
Provides-Extra: metadata
Provides-Extra: test
Requires-Dist: coverage[toml]; extra == 'test'
Requires-Dist: pkg-metadata; extra == 'test'
Requires-Dist: pytest; extra == 'test'
